{
  "runId": "1769396959521-7497",
  "startedAt": "2026-01-26T03:09:19.521Z",
  "finishedAt": "2026-01-26T03:13:15.853Z",
  "durationMs": 236332,
  "exitReason": "no-progress",
  "errorMessage": null,
  "timings": {
    "pageGotoMs": 2648
  },
  "picks": {
    "weighted": [
      {
        "question": "How did you place your order",
        "choice": "Popeyes mobile app"
      }
    ],
    "dropdowns": [
      {
        "question": "Including yourself, how many people were in your party",
        "choice": "Two"
      },
      {
        "question": "Including this visit, how many times have you visited this Popeyes",
        "choice": "Two"
      },
      {
        "question": "Please indicate your gender",
        "choice": "Male"
      },
      {
        "question": "Please indicate your age",
        "choice": "25 to 34"
      },
      {
        "question": "Please indicate your annual household income",
        "choice": "$45,000 to $59,999"
      },
      {
        "question": "Please indicate which of the following best describes your background",
        "choice": "White or Caucasian"
      }
    ],
    "menu": [
      "Boneless Chicken"
    ],
    "orderType": "Takeout/Pickup",
    "visitDate": "2026-01-14",
    "visitTime": "12:49 pm",
    "orderTotal": "24.17",
    "toneOverride": "afternoon",
    "complimentPreview": "Big thanks to the window attendant who kept things organized."
  },
  "pagesVisited": 16,
  "textareasFilled": 1,
  "emojisClicked": 8,
  "dropdownsPicked": 6,
  "likelihoodPicked": 2,
  "menuPicked": 1,
  "starsPicked": 11,
  "gridPicked": 7,
  "noThanksClicked": 0
}